hidrocomp/__init__.py
hidrocomp/comparasion/__init__.py
hidrocomp/comparasion/bootstrap_build.py
hidrocomp/comparasion/genpareto.py
hidrocomp/comparasion/mae.py
hidrocomp/comparasion/quantify_uncertainty.py
hidrocomp/comparasion/rmae.py
hidrocomp/comparasion/rmse.py
hidrocomp/eflow/__init__.py
hidrocomp/eflow/aspect.py
hidrocomp/eflow/era.py
hidrocomp/eflow/exceptions.py
hidrocomp/eflow/graphics.py
hidrocomp/eflow/iha.py
hidrocomp/eflow/rva.py
hidrocomp/files/__init__.py
hidrocomp/files/ana.py
hidrocomp/files/cemaden.py
hidrocomp/files/chesf.py
hidrocomp/files/fileRead.py
hidrocomp/files/fileWrite.py
hidrocomp/files/files.py
hidrocomp/files/nasa.py
hidrocomp/files/ons.py
hidrocomp/files/semarh.py
hidrocomp/graphics/__init__.py
hidrocomp/graphics/boxplot.py
hidrocomp/graphics/comparationdistribution.py
hidrocomp/graphics/distribution_build.py
hidrocomp/graphics/gantt.py
hidrocomp/graphics/genextreme.py
hidrocomp/graphics/genpareto.py
hidrocomp/graphics/hydrogram_annual.py
hidrocomp/graphics/hydrogram_build.py
hidrocomp/graphics/hydrogram_by_year.py
hidrocomp/graphics/hydrogram_clean.py
hidrocomp/graphics/hydrogram_parcial.py
hidrocomp/graphics/polar.py
hidrocomp/graphics/rating_curve.py
hidrocomp/series/__init__.py
hidrocomp/series/__parcial.py
hidrocomp/series/exceptions.py
hidrocomp/series/flow.py
hidrocomp/series/height.py
hidrocomp/series/maximum.py
hidrocomp/series/minimum.py
hidrocomp/series/partial.py
hidrocomp/series/rainfall.py
hidrocomp/series/series_build.py
hidrocomp/statistic/__init__.py
hidrocomp/statistic/bootstrap.py
hidrocomp/statistic/exceptions.py
hidrocomp/statistic/genextre.py
hidrocomp/statistic/genpareto.py
hidrocomp/statistic/normal.py
hidrocomp/statistic/pearson3.py
hidrocomp/statistic/stats_build.py
hidrocomp-1.2.32.dist-info/LICENSE
hidrocomp-1.2.32.dist-info/METADATA
hidrocomp-1.2.32.dist-info/WHEEL
hidrocomp-1.2.32.dist-info/top_level.txt
hidrocomp-1.2.32.dist-info/RECORD
