Metadata-Version: 2.1
Name: hidrocomp
Version: 1.2.32
Summary: Developed for hydrological studies
Home-page: https://github.com/clebsonpy/HidroComp
Author: Clebson Farias
Author-email: clebson2007.farias@gmail.com
License: MIT License
Keywords: hydrology statistic eflow flow
Platform: UNKNOWN
Classifier: Development Status :: 1 - Planning
Classifier: Environment :: Console
Classifier: Intended Audience :: Science/Research
Classifier: Intended Audience :: Developers
Classifier: Intended Audience :: Education
Classifier: License :: OSI Approved :: MIT License
Classifier: Operating System :: OS Independent
Classifier: Programming Language :: Python
Classifier: Topic :: Scientific/Engineering
Classifier: Topic :: Education
Requires-Dist: lmoments3 (==1.0.*)
Requires-Dist: pandas
Requires-Dist: colorlover (==0.3.*)
Requires-Dist: plotly (==4.9.*)
Requires-Dist: pytz (==2020.1)
Requires-Dist: pyzmq (==19.0.*)
Requires-Dist: scipy
Requires-Dist: six (==1.15.*)
Requires-Dist: statsmodels (==0.11.*)
Requires-Dist: hydro-python-api (==1.1.*)
